mkdf/__init__.py
mkdf/cli/__init__.py
mkdf/cli/banner.txt
mkdf/cli/commands/__init__.py
mkdf/cli/commands/create.py
mkdf/cli/commands/interactive.py
mkdf/cli/commands/web.py
mkdf/cli/interfaces/__init__.py
mkdf/cli/interfaces/expert_creation.py
mkdf/cli/interfaces/guided_creation.py
mkdf/cli/interfaces/interactive_actions.py
mkdf/cli/interfaces/interactive_mode.py
mkdf/cli/models/__init__.py
mkdf/cli/models/mappings.py
mkdf/cli/models/ports.py
mkdf/cli/parsers/__init__.py
mkdf/cli/parsers/main_parser.py
mkdf/cli/ui/banner.py
mkdf/cli/ui/panels.py
mkdf/cli/ui/previews.py
mkdf/cli/ui/tables.py
mkdf/cli/validators/__init__.py
mkdf/cli/validators/path.py
mkdf/config/__init__.py
mkdf/config/config_manager.py
mkdf/core.py
mkdf/fs/__init__.py
mkdf/fs/brace_expansion.py
mkdf/fs/dir_creator.py
mkdf/fs/file_creator.py
mkdf/fs/fs_utils.py
mkdf/fs/path_analyzer.py
mkdf/main.py
mkdf/templates/__init__.py
mkdf/templates/base_templates.py
mkdf/templates/docker/__init__.py
mkdf/templates/docker/base/__init__.py
mkdf/templates/docker/base/db_utils.py
mkdf/templates/docker/base/service_template.py
mkdf/templates/docker/registry.py
mkdf/templates/docker/services/__init__.py
mkdf/templates/docker/services/backends/__init__.py
mkdf/templates/docker/services/backends/django.py
mkdf/templates/docker/services/backends/express.py
mkdf/templates/docker/services/backends/fastapi.py
mkdf/templates/docker/services/backends/flask.py
mkdf/templates/docker/services/backends/gofiber.py
mkdf/templates/docker/services/backends/laravel.py
mkdf/templates/docker/services/backends/symfony.py
mkdf/templates/docker/services/databases/__init__.py
mkdf/templates/docker/services/databases/mariadb.py
mkdf/templates/docker/services/databases/mongodb.py
mkdf/templates/docker/services/databases/mysql.py
mkdf/templates/docker/services/databases/postgresql.py
mkdf/templates/docker/services/frontends/__init__.py
mkdf/templates/docker/services/frontends/angular.py
mkdf/templates/docker/services/frontends/nextjs.py
mkdf-0.1.2.dist-info/AUTHORS
mkdf-0.1.2.dist-info/LICENSE
mkdf-0.1.2.dist-info/METADATA
mkdf-0.1.2.dist-info/WHEEL
mkdf-0.1.2.dist-info/entry_points.txt
mkdf-0.1.2.dist-info/RECORD
