Metadata-Version: 2.3
Name: mkdf
Version: 0.1.2
Summary: Make Directories and Files - Professional Project Creator with Rich CLI and Web UI
License: AGPL-3.0
Keywords: cli,project-generator,docker,templates,development,rich,rainbow,web-ui
Author: Fassih Belmokhtar
Author-email: contact@fassih.ch
Requires-Python: >=3.10,<4.0
Classifier: Development Status :: 3 - Alpha
Classifier: Environment :: Console
Classifier: Intended Audience :: Developers
Classifier: License :: OSI Approved :: GNU Affero General Public License v3
Classifier: Operating System :: OS Independent
Classifier: Programming Language :: Python :: 3
Classifier: Programming Language :: Python :: 3.10
Classifier: Programming Language :: Python :: 3.11
Classifier: Programming Language :: Python :: 3.12
Classifier: Programming Language :: Python :: 3.13
Classifier: Topic :: Software Development :: Code Generators
Classifier: Topic :: System :: Software Distribution
Requires-Dist: click (==8.1.7)
Requires-Dist: fastapi (>=0.104.0,<0.105.0)
Requires-Dist: psutil (>=5.9.5,<6.0.0)
Requires-Dist: pydantic (>=2.5.0,<3.0.0)
Requires-Dist: pydantic-settings (>=2.0.0,<3.0.0)
Requires-Dist: requests (>=2.31.0,<3.0.0)
Requires-Dist: rich (>=13.0.0,<14.0.0)
Requires-Dist: sqlmodel (>=0.0.14,<0.0.15)
Requires-Dist: typer (==0.9.0)
Requires-Dist: uvicorn[standard] (>=0.24.0,<0.25.0)
Project-URL: Bug Tracker, https://github.com/Noziop/mkdf-py/issues
Project-URL: Changelog, https://github.com/Noziop/mkdf-py/blob/main/CHANGELOG.md
Project-URL: Documentation, https://github.com/Noziop/mkdf#readme
Project-URL: Homepage, https://github.com/Noziop/mkdf
Project-URL: Repository, https://github.com/Noziop/mkdf
